Metadata-Version: 1.0
Name: deepcadlyx
Version: 0.0.2
Summary: implemenent deepcad to denoise data by removing independent noise
Home-page: https://github.com/STAR-811
Author: YixinLi
Author-email: 20185414@stu.neu.edu.cn
License: MIT Licence
Platform: UNKNOWN
